oscal_dataclass/assessment-plan.py
oscal_dataclass/assessment-results.py
oscal_dataclass/catalog.py
oscal_dataclass/complete.py
oscal_dataclass/component.py
oscal_dataclass/poam.py
oscal_dataclass/profile.py
oscal_dataclass/ssp.py
oscal_pydantic/__init__.py
oscal_pydantic/assessment_plan.py
oscal_pydantic/assessment_results.py
oscal_pydantic/catalog.py
oscal_pydantic/complete.py
oscal_pydantic/component.py
oscal_pydantic/poam.py
oscal_pydantic/profile.py
oscal_pydantic/ssp.py
oscal_pydantic-2023.3.21.dist-info/LICENSE
oscal_pydantic-2023.3.21.dist-info/METADATA
oscal_pydantic-2023.3.21.dist-info/WHEEL
oscal_pydantic-2023.3.21.dist-info/top_level.txt
oscal_pydantic-2023.3.21.dist-info/RECORD
