Metadata-Version: 2.1
Name: oscal-pydantic
Version: 2023.3.21
Summary: A set of Pydantic models generated from the OSCAL specification.
Author-email: Robert Sherwood <robert.sherwood@credentive.com>
Project-URL: Homepage, https://github.com/RS-Credentive/oscal-pydantic
Keywords: oscal,OSCAL,pydantic
Requires-Python: >=3.7
License-File: LICENSE
Requires-Dist: pydantic
